pystraksexplorer/__init__.py
pystraksexplorer/pystraksexplorer.py
pystraksexplorer/stocksexchange.py
pystraksexplorer-1.1.0.dist-info/DESCRIPTION.rst
pystraksexplorer-1.1.0.dist-info/METADATA
pystraksexplorer-1.1.0.dist-info/RECORD
pystraksexplorer-1.1.0.dist-info/WHEEL
pystraksexplorer-1.1.0.dist-info/entry_points.txt
pystraksexplorer-1.1.0.dist-info/metadata.json
pystraksexplorer-1.1.0.dist-info/top_level.txt
