Metadata-Version: 2.0
Name: pystraksexplorer
Version: 1.1.0
Summary: Python wrapper for STRAKS block explorer api
Home-page: UNKNOWN
Author: Freeman
Author-email: fr3eman@protonmail.com
License: MIT
Keywords: straks blockexplorer crypto api
Platform: UNKNOWN
Classifier: Programming Language :: Python :: 2
Classifier: Programming Language :: Python :: 2.6
Classifier: Programming Language :: Python :: 2.7
Classifier: Programming Language :: Python :: 3
Classifier: Programming Language :: Python :: 3.2
Classifier: Programming Language :: Python :: 3.3
Classifier: Programming Language :: Python :: 3.4
Requires-Dist: requests
